xmlJoiner/__init__.py
xmlJoiner/console.py
xmlJoiner/constants.py
xmlJoiner/loginit.py
xmlJoiner/version.py
xmlJoiner/xmlJoin.py
xmlJoiner-0.1.1.dist-info/LICENSE
xmlJoiner-0.1.1.dist-info/METADATA
xmlJoiner-0.1.1.dist-info/WHEEL
xmlJoiner-0.1.1.dist-info/entry_points.txt
xmlJoiner-0.1.1.dist-info/top_level.txt
xmlJoiner-0.1.1.dist-info/RECORD
