Metadata-Version: 2.1
Name: xmlJoiner
Version: 0.1.1
Summary: ESA EDDS XML Telemetry joiner
Author-email: Romolo Politi <Romolo.Politi@inaf.it>
License: GNU GPL ver3
Project-URL: Repository, https://github.com/RomoloPoliti-INAF/xmlJoiner
Keywords: ESA,Space Mission,Telemetry
Classifier: Development Status :: 2 - Pre-Alpha
Classifier: License :: OSI Approved :: GNU General Public License v3 (GPLv3)
License-File: LICENSE
Requires-Dist: rich-click
Requires-Dist: rich
Requires-Dist: importlib-metadata ; python_version > "3.10"
Provides-Extra: docs
Requires-Dist: sphinx ; extra == 'docs'
